CircleciLibrary/__init__.py
CircleciLibrary/keywords.py
CircleciLibrary/log.py
CircleciLibrary/model.py
robotframework_circlecilibrary-0.1.3.dist-info/LICENSE
robotframework_circlecilibrary-0.1.3.dist-info/METADATA
robotframework_circlecilibrary-0.1.3.dist-info/WHEEL
robotframework_circlecilibrary-0.1.3.dist-info/top_level.txt
robotframework_circlecilibrary-0.1.3.dist-info/RECORD
