Metadata-Version: 2.1
Name: robotframework-circlecilibrary
Version: 0.1.3
Summary: A robotframework extension to run circleci pipelines
Home-page: https://github.com/trustedshops-public/robotframework-circlecilibrary
Author: Thomas Volk
Author-email: thomas.volk@trustedshops.com
License: Apache License 2.0
Platform: any
Classifier: Programming Language :: Python :: 3.9
Classifier: License :: OSI Approved :: Apache Software License
Classifier: Operating System :: OS Independent
Classifier: Topic :: Software Development :: Testing
Classifier: Topic :: Software Development :: Testing :: Acceptance
Classifier: Framework :: Robot Framework
Requires-Python: >=3.9.0
Requires-Dist: pycircleci (>=0.3.2)
Requires-Dist: robotframework (>=4.0.0)
